swisstime/__init__.py
swisstime-0.9.0.dist-info/DESCRIPTION.rst
swisstime-0.9.0.dist-info/METADATA
swisstime-0.9.0.dist-info/RECORD
swisstime-0.9.0.dist-info/WHEEL
swisstime-0.9.0.dist-info/metadata.json
swisstime-0.9.0.dist-info/top_level.txt
