Metadata-Version: 2.0
Name: swisstime
Version: 0.9.0
Summary: Time the performance of portions of code and produce a report when done.
Home-page: https://github.com/built/swisstime
Author: Matt Youell
Author-email: matt@youell.com
License: MIT
Keywords: development diagnostics
Platform: UNKNOWN
Classifier: Development Status :: 4 - Beta
Classifier: Intended Audience :: Developers
Classifier: Topic :: Software Development :: Quality Assurance
Classifier: License :: OSI Approved :: MIT License
Classifier: Programming Language :: Python :: 2
Classifier: Programming Language :: Python :: 2.6
Classifier: Programming Language :: Python :: 2.7
Classifier: Programming Language :: Python :: 3
Classifier: Programming Language :: Python :: 3.2
Classifier: Programming Language :: Python :: 3.3
Classifier: Programming Language :: Python :: 3.4
Classifier: Programming Language :: Python :: 3.5
